{
  "pymdp_agent_integration": {
    "agent_creation_successful": true,
    "transition_models_tested": true,
    "multi_step_simulation_completed": true,
    "methods_demonstrated": [
      "Agent",
      "infer_states",
      "infer_policies",
      "sample_action"
    ]
  },
  "deterministic_transitions": [
    [
      [
        1.0,
        0.0
      ],
      [
        0.0,
        0.0
      ],
      [
        0.0,
        0.0
      ]
    ],
    [
      [
        0.0,
        1.0
      ],
      [
        1.0,
        0.0
      ],
      [
        1.0,
        0.0
      ]
    ],
    [
      [
        0.0,
        0.0
      ],
      [
        0.0,
        1.0
      ],
      [
        0.0,
        1.0
      ]
    ]
  ],
  "stochastic_transitions": [
    [
      [
        1.0,
        0.15
      ],
      [
        0.8,
        0.05
      ],
      [
        0.05,
        0.0
      ]
    ],
    [
      [
        0.0,
        0.8
      ],
      [
        0.15,
        0.15
      ],
      [
        0.8,
        0.0
      ]
    ],
    [
      [
        0.0,
        0.05
      ],
      [
        0.05,
        0.8
      ],
      [
        0.15,
        1.0
      ]
    ]
  ],
  "multi_action_robot": [
    [
      [
        0.0,
        0.0,
        0.9
      ],
      [
        0.0,
        1.0,
        0.1
      ],
      [
        0.0,
        0.0,
        0.1
      ],
      [
        1.0,
        0.0,
        0.1
      ]
    ],
    [
      [
        1.0,
        0.0,
        0.1
      ],
      [
        0.0,
        0.0,
        0.9
      ],
      [
        0.0,
        1.0,
        0.1
      ],
      [
        0.0,
        0.0,
        0.1
      ]
    ],
    [
      [
        0.0,
        0.0,
        0.1
      ],
      [
        1.0,
        0.0,
        0.1
      ],
      [
        0.0,
        0.0,
        0.9
      ],
      [
        0.0,
        1.0,
        0.1
      ]
    ],
    [
      [
        0.0,
        1.0,
        0.1
      ],
      [
        0.0,
        0.0,
        0.1
      ],
      [
        1.0,
        0.0,
        0.1
      ],
      [
        0.0,
        0.0,
        0.9
      ]
    ]
  ],
  "temporal_traffic": [
    [
      [
        0.1,
        0.0
      ],
      [
        0.0,
        0.0
      ],
      [
        0.8,
        0.0
      ]
    ],
    [
      [
        0.8,
        0.0
      ],
      [
        0.2,
        0.0
      ],
      [
        0.0,
        0.0
      ]
    ],
    [
      [
        0.1,
        1.0
      ],
      [
        0.8,
        1.0
      ],
      [
        0.2,
        1.0
      ]
    ]
  ],
  "prediction_trajectory": [
    [
      0.3333333333333333,
      0.3333333333333333,
      0.3333333333333333
    ],
    [
      0.06666666666666667,
      0.31666666666666665,
      0.6166666666666667
    ],
    [
      0.025833333333333333,
      0.10083333333333333,
      0.8733333333333334
    ],
    [
      0.15016666666666667,
      0.7137916666666668,
      0.13604166666666667
    ],
    [
      0.7280020833333335,
      0.21590208333333336,
      0.056095833333333345
    ]
  ],
  "action_sequence": [
    1,
    1,
    0,
    0
  ],
  "model_concepts": {
    "deterministic": "Actions have certain, predictable effects",
    "stochastic": "Actions have probabilistic effects with noise",
    "multi_action": "Different actions create qualitatively different dynamics",
    "temporal": "Transitions encode time-dependent patterns and sequences",
    "prediction": "B matrices enable forward simulation for planning"
  }
}